xmltopy
