Metadata-Version: 1.0
Name: xmltopy
Version: 1.1.18
Summary: Utilities for manipulating XML
Home-page: http://code.google.com/p/xmltopy/
Author: Matt Hanger
Author-email: matt@matthanger.net
License: MIT
Platform: UNKNOWN
Classifier: License :: OSI Approved :: MIT License
Classifier: Operating System :: OS Independent
